pdpilot/__init__.py
pdpilot/_frontend.py
pdpilot/_version.py
pdpilot/logging.py
pdpilot/metadata.py
pdpilot/pdp.py
pdpilot/tqdm_joblib.py
pdpilot/utils.py
pdpilot/widget.py
pdpilot/labextension/package.json
pdpilot/labextension/static/509.bd0f74b4268e70e813a4.js
pdpilot/labextension/static/568.1387ee2f117f71b79c0e.js
pdpilot/labextension/static/568.4fc56f21798f6893e802.js
pdpilot/labextension/static/568.53592afa59a85b0d5ddf.js
pdpilot/labextension/static/568.75a3dc5b401ab1be6460.js
pdpilot/labextension/static/568.8a58609c168e2e65e07d.js
pdpilot/labextension/static/568.8c1ec5714e48a5d9339f.js
pdpilot/labextension/static/568.8c693d68889c86f2e591.js
pdpilot/labextension/static/568.9e79624a4e48057d0655.js
pdpilot/labextension/static/568.a05a3fc2d170aab3b7e4.js
pdpilot/labextension/static/568.b6550321e291f730c26f.js
pdpilot/labextension/static/568.b93e2c1943a13cb87ff9.js
pdpilot/labextension/static/568.bae57007d7cd1d47ef8a.js
pdpilot/labextension/static/568.be4561957748b400120d.js
pdpilot/labextension/static/568.c13d41421ddce7a31709.js
pdpilot/labextension/static/568.f79ad2c6933bd9946421.js
pdpilot/labextension/static/568.fc735409708fd22de78c.js
pdpilot/labextension/static/7.88f5d79135fb93a5f5c1.js
pdpilot/labextension/static/7.88f5d79135fb93a5f5c1.js.LICENSE.txt
pdpilot/labextension/static/713.4cbf2d1872080e10ff0b.js
pdpilot/labextension/static/713.4cbf2d1872080e10ff0b.js.LICENSE.txt
pdpilot/labextension/static/713.5fb1220914a3fc9b6db7.js
pdpilot/labextension/static/713.5fb1220914a3fc9b6db7.js.LICENSE.txt
pdpilot/labextension/static/713.90e9e8591918308584e8.js
pdpilot/labextension/static/713.90e9e8591918308584e8.js.LICENSE.txt
pdpilot/labextension/static/713.99b649b8951ffd670735.js
pdpilot/labextension/static/713.99b649b8951ffd670735.js.LICENSE.txt
pdpilot/labextension/static/remoteEntry.07d18582b6cb1e9fa682.js
pdpilot/labextension/static/remoteEntry.18df620b0ae7af7c0cdf.js
pdpilot/labextension/static/remoteEntry.5216e468fe53fd73417b.js
pdpilot-0.6.1.dist-info/LICENSE.txt
pdpilot-0.6.1.dist-info/METADATA
pdpilot-0.6.1.dist-info/WHEEL
pdpilot-0.6.1.dist-info/top_level.txt
pdpilot-0.6.1.dist-info/RECORD
